{
    "server": {
        "services": [{
            "name":"GitHub",
            "description":"Github est une entreprise de développement et services logiciels sise aux États-Unis. Github développe notamment la plateforme Github, la structure Electron.",
            "logo_url": "https://upload.wikimedia.org/wikipedia/commons/thumb/9/95/Font_Awesome_5_brands_github.svg/1200px-Font_Awesome_5_brands_github.svg.png",
            "actions": [{
                "name":"push on repository",
                "actionId": 1,
                "description":"A push is made on a repository",
                "params": [{"repo": "repository_name"}]
                    }, {
                "name":"pull request on repository",
                "actionId": 2,
                "description":"A pull request is made on a repository",
                "params": [{"repo": "repository_name"}]
                    }, {
                "name":"issue on repository",
                "actionId": 3,
                "description":"An issue is made on a repository",
                "params": [{"repo": "repository_name"}]
                    }, {
                "name": "create branch",
                "actionId": 4,
                "description": "A branch is created on a repository",
                "params": [{"repo": "repository_name"}]
                    }],
            "reactions": [{
                "name":"create issue",
                "reactionId": 1,
                "description":"Create an issue on a repository",
                "params": [{"repo": "repository_name", "title": "issue_title", "body": "issue_body", "assignees": "issue_assignees", "milestone":"milestones","labels": "issue_labels"}]
                    },{
                "name":"create pull request",
                "reactionId": 2,
                "description":"Create a pull request on a repository",
                "params": [{"repo": "repository_name", "title": "pull_request_title", "body": "pull_request_body", "head": "pull_request_head", "base": "pull_request_base"}]
                    }
                ]
            },{
            "name": "Google",
            "description": "Google est une entreprise américaine de services technologiques fondée en 1998 dans la Silicon Valley, en Californie, par Larry Page et Sergey Brin, créateurs du moteur de recherche Google. C'est une filiale de la société Alphabet depuis août 2015.",
            "logo_url": "https://upload.wikimedia.org/wikipedia/commons/thumb/5/53/Google_%22G%22_Logo.svg/800px-Google_%22G%22_Logo.svg.png"
            },{
            "name": "Mail",
            "description": "Un courrier électronique, également nommé courriel, mel ou e-mail, est un message écrit, envoyé électroniquement via un réseau informatique. On appelle messagerie électronique l'ensemble du système qui permet la transmission des courriels.",
            "logo_url": "https://upload.wikimedia.org/wikipedia/fr/a/a7/Mail_%28Apple%29_logo.png",
            "reactions": []
            },{
            "name": "Microsoft",
            "description": "Microsoft Corporation est une multinationale informatique et micro-informatique américaine, fondée en 1975 par Bill Gates et Paul Allen. Microsoft fait partie des principales capitalisations boursières du NASDAQ, aux côtés d'Apple et d'Amazon. En 2018, le chiffre d'affaires s’élevait à 110,36 milliards de dollars.",
            "logo_url": "https://download.logo.wine/logo/Microsoft_Outlook/Microsoft_Outlook-Logo.wine.png",
            "actions" : [{
                "name": "Receive mail",
                "actionId": 5,
                "description": "When you receive a mail",
                "params": [{}]
                }],
            "reactions":[{
                "name": "create event",
                "reactionId": 4,
                "description": "Create an event in your calendar",
                "params": [{"title": "event_title", "start": "event_start(format: YYYY/MM/DD)", "end": "event_end(format: YYYY/MM/DD)"}]
                },{
                "name": "create draft",
                "reactionId": 9,
                "description": "create a draft mail",
                "params": [{"to": "mail_to", "subject": "mail_subject", "body": "mail_body"}]
                },{
                "name": "Create Calendar Group",
                "reactionId": 10,
                "description": "create a calendar group",
                "params": [{"name": "name of the group"}]
                },{
                "name": "Create Calendar",
                "reactionId": 11,
                "description": "create a calendar",
                "params": [{"name": "name of the calendar"}]
                },{
                "name": "Create Outlook Category",
                "reactionId": 12,
                "description": "create a category",
                "params": [{"displayName": "name of the category"}]
                },{
                }]
            },{
            "name": "Spotify",
            "description": "Spotify est un service suédois de streaming musical sous la forme d'un logiciel propriétaire et d'un site web. Cette plateforme de distribution numérique permet une écoute quasi instantanée de fichiers musicaux.",
            "logo_url": "https://upload.wikimedia.org/wikipedia/commons/thumb/1/19/Spotify_logo_without_text.svg/768px-Spotify_logo_without_text.svg.png",
            "actions": [],
            "reactions": [{
                "name": "create playlist",
                "reactionId": 5,
                "description": "create a playlist",
                "params": [{"playlist": "playlist_name"}]
            }, {
                "name": "add item to playlist",
                "reactionId": 6,
                "description": "add a track to a playlist",
                "params": [{"playlist_id": "playlist_id", "item_uri": "item"}]
            }, {
                "name": "delete item from playlist",
                "reactionId": 7,
                "description": "delete a track from a playlist",
                "params": [{"playlist_id": "playlist_id", "item_uri": "item"}]
            }, {
                "name": "change playlist details",
                "reactionId": 8,
                "description": "change the details of a playlist",
                "params": [{"playlist_id": "playlist_id", "new_playlist_name": "new_playlist_name", "new_playlist_description": "new_playlist_description"}]
            }, {
                "name": "save playlist",
                "reactionId": 16,
                "description": "save a playlist on user's library",
                "params": [{"playlist_id": "playlist_id"}]
            }, {
                "name": "remove playlist",
                "reactionId": 17,
                "description": "remove a playlist from user's library",
                "params": [{"playlist_id": "playlist_id"}]
            }
        ]
        }, {
            "name": "Instagram",
            "description": "Instagram est une application, un réseau social et un service de partage de photos et de vidéos fondés et lancés en octobre 2010 par l'Américain Kevin Systrom et le Brésilien Michel Mike Krieger.",
            "logo_url": "https://upload.wikimedia.org/wikipedia/commons/thumb/5/58/Instagram-Icon.png/768px-Instagram-Icon.png",
            "actions": [],
            "reactions": []
        }, {
            "name": "Notion",
            "description": "Notion est un logiciel de prise de notes et de gestion de projets. Il est disponible sur navigateur web, macOS, iOS et Android. Il est développé par Notion Labs Inc, une start-up basée à San Francisco.",
            "logo_url": "https://upload.wikimedia.org/wikipedia/commons/thumb/4/45/Notion_app_logo.png/768px-Notion_app_logo.png",
            "actions": [],
            "reactions": [{
                "name": "create page notion",
                "reactionId": 13,
                "description": "create a page",
                "params": [{"parent_id": "parent", "title": "title"}]
                }, {
                "name": "create comment notion",
                "reactionId": 14,
                "description": "create a comment",
                "params": [{"parent_id": "parent", "comment": "comment"}]
            }]
        }, {
            "name": "Figma",
            "description": "Figma est un outil de conception d'interface utilisateur et de prototypage basé sur le Web, avec une option de partage en temps réel. Il permet aux utilisateurs de collaborer sur un projet en temps réel et de modifier le même fichier. Le logiciel est disponible pour les systèmes d'exploitation Windows et macOS.",
            "logo_url": "https://upload.wikimedia.org/wikipedia/commons/thumb/3/33/Figma-logo.svg/768px-Figma-logo.svg.png",
            "actions": [],
            "reactions": [{
                "name": "Add Comment",
                "reactionId": 15,
                "description": "Add a comment",
                "params": [{"file_key": "file key", "comment": "message"}]
            }]
        }]
    }
}
